README.md
setup.py
pyseisdl/__init__.py
pyseisdl/denoise.py
pyseisdl/ksvd.py
pyseisdl/patch.py
pyseisdl/sgk.py
pyseisdl/snr.py
pyseisdl/threshold.py
pyseisdl.egg-info/PKG-INFO
pyseisdl.egg-info/SOURCES.txt
pyseisdl.egg-info/dependency_links.txt
pyseisdl.egg-info/not-zip-safe
pyseisdl.egg-info/requires.txt
pyseisdl.egg-info/top_level.txt