Metadata-Version: 2.1
Name: pyseisdl
Version: 0.0.1
Summary: A python package for different dictionary learning methods and their applications in seismology. DL has a variety of applications in seismology, including but not limited to seismic denoising, seismic reconstruction, seismic diffraction separation, constrained LSRTM, constrained FWI, etc.
Home-page: https://github.com/chenyk1990/pyseisdl
Author: pyseisdl developing team
Author-email: chenyk2016@gmail.com
License: GNU General Public License, Version 3 (GPLv3)
Keywords: seismology,exploration seismology,array seismology,denoising,science,signal-to-noise ratio,dictionary learning
Platform: UNKNOWN
Classifier: Development Status :: 4 - Beta
Classifier: Intended Audience :: Developers
Classifier: Intended Audience :: Science/Research
Classifier: Operating System :: Unix
Classifier: Operating System :: POSIX
Classifier: Operating System :: Microsoft :: Windows
Classifier: Programming Language :: Python
Classifier: Programming Language :: Python :: 3.8
Classifier: Programming Language :: Python :: Implementation :: CPython
Classifier: Topic :: Scientific/Engineering
Classifier: Topic :: Scientific/Engineering :: Physics
Classifier: License :: OSI Approved :: GNU General Public License v3 (GPLv3)
Provides-Extra: docs
